drkp.py
drkp-0.1.0.dist-info/LICENSE
drkp-0.1.0.dist-info/WHEEL
drkp-0.1.0.dist-info/METADATA
drkp-0.1.0.dist-info/RECORD
