Metadata-Version: 2.1
Name: drkp
Version: 0.1.0
Summary: Deterministic RSA Key Pair generator.
Author-email: Chris Coleman <chris@chriscoleman.uk>
Classifier: License :: OSI Approved :: MIT License
Requires-Dist: gmpy2
Requires-Dist: paramiko
Requires-Dist: rsa
